pipepy/__init__.py
pipepy/exceptions.py
pipepy/misc.py
pipepy/pipepy.py
pipepy/pymake.py
pipepy/utils.py
tests/__init__.py
tests/test_background.py
tests/test_context_processor.py
tests/test_exceptions.py
tests/test_misc.py
tests/test_modify.py
tests/test_output.py
tests/test_pipes.py
tests/test_pymake.py
tests/utils.py
pipepy-0.0.11.dist-info/LICENSE
pipepy-0.0.11.dist-info/METADATA
pipepy-0.0.11.dist-info/WHEEL
pipepy-0.0.11.dist-info/entry_points.txt
pipepy-0.0.11.dist-info/top_level.txt
pipepy-0.0.11.dist-info/RECORD
