Metadata-Version: 2.1
Name: pipepy
Version: 0.0.11
Summary: A Python library for invoking and interacting with shell commands
Home-page: https://github.com/kbairak/pipepy
Author: Konstantinos Bairaktaris
Author-email: ikijob@gmail.com
Classifier: Programming Language :: Python :: 3
Classifier: License :: OSI Approved :: GNU General Public License v3 (GPLv3)
Classifier: Operating System :: OS Independent
Requires-Python: >=3.7
License-File: LICENSE
